[
	{
		"link": "https://www.applyhome.co.kr/ai/aia/selectAPTLttotPblancDetail.do?houseManageNo=2022000601&pblancNo=2022000601&houseSecd=01",
		"in_date": "20220913",
		"hsecd": "01",
		"rse": "01",
		"type": "APT 특별공급",
		"name": "광혜원 포레가",
		"addr": "충청북도 진천군 광혜원면 화랑길 64-14",
		"short_addr": "충청북도 진천군",
		"addr_lv1": "충청북도",
		"addr_lv2": "진천군",
		"apply_nums": "51세대"
	},
	{
		"link": "https://www.applyhome.co.kr/ai/aia/selectAPTLttotPblancDetail.do?houseManageNo=2022000490&pblancNo=2022000490&houseSecd=01",
		"in_date": "20220913",
		"hsecd": "01",
		"rse": "01",
		"type": "APT 특별공급",
		"name": "구서다움파크",
		"addr": "부산광역시 금정구 중앙대로1893번길 50(구서동)",
		"short_addr": "부산광역시 금정구",
		"addr_lv1": "부산광역시",
		"addr_lv2": "금정구",
		"apply_nums": "84세대"
	},
	{
		"link": "https://www.applyhome.co.kr/ai/aia/selectAPTLttotPblancDetail.do?houseManageNo=2022000575&pblancNo=2022000575&houseSecd=01",
		"in_date": "20220913",
		"hsecd": "01",
		"rse": "01",
		"type": "APT 특별공급",
		"name": "양양 스위트엠 디오션",
		"addr": "강원도 양양군 양양읍 청곡리 87-7 번지 외 16필지 ",
		"short_addr": "강원도 양양군",
		"addr_lv1": "강원도",
		"addr_lv2": "양양군",
		"apply_nums": "209세대"
	},
	{
		"link": "https://www.applyhome.co.kr/ai/aia/selectAPTLttotPblancDetail.do?houseManageNo=2022000557&pblancNo=2022000557&houseSecd=01",
		"in_date": "20220913",
		"hsecd": "01",
		"rse": "01",
		"type": "APT 특별공급",
		"name": "평촌 두산위브 더 프라임",
		"addr": "경기도 안양시 동안구 호계3동 651-1번지 일원",
		"short_addr": "경기도 안양시",
		"addr_lv1": "경기도",
		"addr_lv2": "안양시",
		"apply_nums": "178세대"
	},
	{
		"link": "https://www.applyhome.co.kr/ai/aia/selectAPTRemndrLttotPblancDetailView.do?houseManageNo=2022910291&pblancNo=2022910291&houseSecd=04",
		"in_date": "20220913",
		"hsecd": "04",
		"rse": "06",
		"type": "무순위/취소후재공급",
		"name": "라펜트 힐",
		"addr": "광주광역시 광산구 월계동 870-1번지 일원",
		"short_addr": "광주광역시 광산구",
		"addr_lv1": "광주광역시",
		"addr_lv2": "광산구",
		"apply_nums": "2세대"
	},
	{
		"link": "https://www.applyhome.co.kr/ai/aia/selectAPTRemndrLttotPblancDetailView.do?houseManageNo=2022910285&pblancNo=2022910285&houseSecd=04",
		"in_date": "20220913",
		"hsecd": "04",
		"rse": "06",
		"type": "무순위/취소후재공급",
		"name": "문수로 푸르지오 어반피스(청약전 반드시 대표전화 문의 재당첨 제한 7년, 울산거주자,무주택자만 해당)",
		"addr": "울산광역시 남구 신정동 1266-6번지 일원",
		"short_addr": "울산광역시 남구",
		"addr_lv1": "울산광역시",
		"addr_lv2": "남구",
		"apply_nums": "9세대"
	},
	{
		"link": "https://www.applyhome.co.kr/ai/aia/selectAPTRemndrLttotPblancDetailView.do?houseManageNo=2022910283&pblancNo=2022910283&houseSecd=04",
		"in_date": "20220913",
		"hsecd": "04",
		"rse": "06",
		"type": "무순위/취소후재공급",
		"name": "서면4차 봄여름가을겨울",
		"addr": "부산광역시 부산진구 당감동 866-1번지 일원",
		"short_addr": "부산광역시 부산진구",
		"addr_lv1": "부산광역시",
		"addr_lv2": "부산진구",
		"apply_nums": "183세대"
	},
	{
		"link": "https://www.applyhome.co.kr/ai/aia/selectAPTRemndrLttotPblancDetailView.do?houseManageNo=2022910294&pblancNo=2022910294&houseSecd=04",
		"in_date": "20220913",
		"hsecd": "04",
		"rse": "06",
		"type": "무순위/취소후재공급",
		"name": "선운 더브이 레브리티",
		"addr": "광주광역시 광산구 선암동 358-5번지 일원",
		"short_addr": "광주광역시 광산구",
		"addr_lv1": "광주광역시",
		"addr_lv2": "광산구",
		"apply_nums": "66세대"
	},
	{
		"link": "https://www.applyhome.co.kr/ai/aia/selectAPTRemndrLttotPblancDetailView.do?houseManageNo=2022910288&pblancNo=2022910288&houseSecd=04",
		"in_date": "20220913",
		"hsecd": "04",
		"rse": "06",
		"type": "무순위/취소후재공급",
		"name": "소사역 한라비발디 프레스티지",
		"addr": "경기도 부천시 소사본동 70-12",
		"short_addr": "경기도 부천시",
		"addr_lv1": "경기도",
		"addr_lv2": "부천시",
		"apply_nums": "4세대"
	},
	{
		"link": "https://www.applyhome.co.kr/ai/aia/selectAPTRemndrLttotPblancDetailView.do?houseManageNo=2022910296&pblancNo=2022910296&houseSecd=04",
		"in_date": "20220913",
		"hsecd": "04",
		"rse": "06",
		"type": "무순위/취소후재공급",
		"name": "송도 Luxe Ocean SK VIEW (청약접수전 반드시 대표전화 문의, 재당첨제한 10년, 인천시 거주자/무주택자만 해당)",
		"addr": "인천광역시 연수구 송도동 396-1(송도랜드마크시티 6, 8공구 A9블록)",
		"short_addr": "인천광역시 연수구",
		"addr_lv1": "인천광역시",
		"addr_lv2": "연수구",
		"apply_nums": "4세대"
	},
	{
		"link": "https://www.applyhome.co.kr/ai/aia/selectAPTRemndrLttotPblancDetailView.do?houseManageNo=2022910290&pblancNo=2022910290&houseSecd=04",
		"in_date": "20220913",
		"hsecd": "04",
		"rse": "06",
		"type": "무순위/취소후재공급",
		"name": "신림스카이아파트",
		"addr": "서울특별시 관악구 신림로 185(신림동, 신림 스카이 아파트)",
		"short_addr": "서울특별시 관악구",
		"addr_lv1": "서울특별시",
		"addr_lv2": "관악구",
		"apply_nums": "4세대"
	},
	{
		"link": "https://www.applyhome.co.kr/ai/aia/selectAPTRemndrLttotPblancDetailView.do?houseManageNo=2022910292&pblancNo=2022910292&houseSecd=04",
		"in_date": "20220913",
		"hsecd": "04",
		"rse": "06",
		"type": "무순위/취소후재공급",
		"name": "유보라 천안 두정역",
		"addr": "충청남도 천안시 서북구 두정동 393-21번지 일원",
		"short_addr": "충청남도 천안시",
		"addr_lv1": "충청남도",
		"addr_lv2": "천안시",
		"apply_nums": "280세대"
	},
	{
		"link": "https://www.applyhome.co.kr/ai/aia/selectAPTRemndrLttotPblancDetailView.do?houseManageNo=2022910284&pblancNo=2022910284&houseSecd=04",
		"in_date": "20220913",
		"hsecd": "04",
		"rse": "06",
		"type": "무순위/취소후재공급",
		"name": "전주 효자 엘르디움 에듀파크 아파트(청약전 반드시 대표전화 문의, 재당첨제한 7년, 전주시 거주자/무주택자만 해당)",
		"addr": "전라북도 전주시 완산구 효자동2가 1117-146번지 일원",
		"short_addr": "전라북도 전주시",
		"addr_lv1": "전라북도",
		"addr_lv2": "전주시",
		"apply_nums": "40세대"
	},
	{
		"link": "https://www.applyhome.co.kr/ai/aia/selectAPTRemndrLttotPblancDetailView.do?houseManageNo=2022910287&pblancNo=2022910287&houseSecd=04",
		"in_date": "20220913",
		"hsecd": "04",
		"rse": "06",
		"type": "무순위/취소후재공급",
		"name": "초읍 월드메르디앙 에듀포레(청약접수전 재당첨제한 7년 확인요망)",
		"addr": "부산광역시 부산진구 초읍동 529-14번지 일원",
		"short_addr": "부산광역시 부산진구",
		"addr_lv1": "부산광역시",
		"addr_lv2": "부산진구",
		"apply_nums": "4세대"
	},
	{
		"link": "https://www.applyhome.co.kr/ai/aia/selectAPTRemndrLttotPblancDetailView.do?houseManageNo=2022910286&pblancNo=2022910286&houseSecd=04",
		"in_date": "20220913",
		"hsecd": "04",
		"rse": "06",
		"type": "무순위/취소후재공급",
		"name": "현대 프라힐스 소사역 더프라임",
		"addr": "경기도 부천시 소사본동 70-7외 6필지",
		"short_addr": "경기도 부천시",
		"addr_lv1": "경기도",
		"addr_lv2": "부천시",
		"apply_nums": "16세대"
	},
	{
		"link": "https://www.applyhome.co.kr/ai/aia/selectAPTLttotPblancDetail.do?houseManageNo=2022000602&pblancNo=2022000602&houseSecd=01",
		"in_date": "20220914",
		"hsecd": "01",
		"rse": "01",
		"type": "APT 특별공급",
		"name": "e편한세상 주촌 더프리미어",
		"addr": "경상남도 김해시 주촌면 선지리213-2번지 일원",
		"short_addr": "경상남도 김해시",
		"addr_lv1": "경상남도",
		"addr_lv2": "김해시",
		"apply_nums": "992세대"
	},
	{
		"link": "https://www.applyhome.co.kr/ai/aia/selectAPTLttotPblancDetail.do?houseManageNo=2022000601&pblancNo=2022000601&houseSecd=01",
		"in_date": "20220914",
		"hsecd": "01",
		"rse": "02",
		"type": "APT 1순위",
		"name": "광혜원 포레가",
		"addr": "충청북도 진천군 광혜원면 화랑길 64-14",
		"short_addr": "충청북도 진천군",
		"addr_lv1": "충청북도",
		"addr_lv2": "진천군",
		"apply_nums": "51세대"
	},
	{
		"link": "https://www.applyhome.co.kr/ai/aia/selectAPTLttotPblancDetail.do?houseManageNo=2022000490&pblancNo=2022000490&houseSecd=01",
		"in_date": "20220914",
		"hsecd": "01",
		"rse": "02",
		"type": "APT 1순위",
		"name": "구서다움파크",
		"addr": "부산광역시 금정구 중앙대로1893번길 50(구서동)",
		"short_addr": "부산광역시 금정구",
		"addr_lv1": "부산광역시",
		"addr_lv2": "금정구",
		"apply_nums": "84세대"
	},
	{
		"link": "https://www.applyhome.co.kr/ai/aia/selectAPTLttotPblancDetail.do?houseManageNo=2022000575&pblancNo=2022000575&houseSecd=01",
		"in_date": "20220914",
		"hsecd": "01",
		"rse": "02",
		"type": "APT 1순위",
		"name": "양양 스위트엠 디오션",
		"addr": "강원도 양양군 양양읍 청곡리 87-7 번지 외 16필지 ",
		"short_addr": "강원도 양양군",
		"addr_lv1": "강원도",
		"addr_lv2": "양양군",
		"apply_nums": "209세대"
	},
	{
		"link": "https://www.applyhome.co.kr/ai/aia/selectAPTLttotPblancDetail.do?houseManageNo=2022000557&pblancNo=2022000557&houseSecd=01",
		"in_date": "20220914",
		"hsecd": "01",
		"rse": "02",
		"type": "APT 1순위",
		"name": "평촌 두산위브 더 프라임",
		"addr": "경기도 안양시 동안구 호계3동 651-1번지 일원",
		"short_addr": "경기도 안양시",
		"addr_lv1": "경기도",
		"addr_lv2": "안양시",
		"apply_nums": "178세대"
	},
	{
		"link": "https://www.applyhome.co.kr/ai/aia/selectAPTRemndrLttotPblancDetailView.do?houseManageNo=2022910286&pblancNo=2022910286&houseSecd=04",
		"in_date": "20220914",
		"hsecd": "04",
		"rse": "06",
		"type": "무순위/취소후재공급",
		"name": "현대 프라힐스 소사역 더프라임",
		"addr": "경기도 부천시 소사본동 70-7외 6필지",
		"short_addr": "경기도 부천시",
		"addr_lv1": "경기도",
		"addr_lv2": "부천시",
		"apply_nums": "16세대"
	},
	{
		"link": "https://www.applyhome.co.kr/ai/aia/selectAPTLttotPblancDetail.do?houseManageNo=2022000602&pblancNo=2022000602&houseSecd=01",
		"in_date": "20220915",
		"hsecd": "01",
		"rse": "02",
		"type": "APT 1순위",
		"name": "e편한세상 주촌 더프리미어",
		"addr": "경상남도 김해시 주촌면 선지리213-2번지 일원",
		"short_addr": "경상남도 김해시",
		"addr_lv1": "경상남도",
		"addr_lv2": "김해시",
		"apply_nums": "992세대"
	},
	{
		"link": "https://www.applyhome.co.kr/ai/aia/selectAPTLttotPblancDetail.do?houseManageNo=2022000490&pblancNo=2022000490&houseSecd=01",
		"in_date": "20220915",
		"hsecd": "01",
		"rse": "02",
		"type": "APT 1순위",
		"name": "구서다움파크",
		"addr": "부산광역시 금정구 중앙대로1893번길 50(구서동)",
		"short_addr": "부산광역시 금정구",
		"addr_lv1": "부산광역시",
		"addr_lv2": "금정구",
		"apply_nums": "84세대"
	},
	{
		"link": "https://www.applyhome.co.kr/ai/aia/selectAPTLttotPblancDetail.do?houseManageNo=2022000557&pblancNo=2022000557&houseSecd=01",
		"in_date": "20220915",
		"hsecd": "01",
		"rse": "02",
		"type": "APT 1순위",
		"name": "평촌 두산위브 더 프라임",
		"addr": "경기도 안양시 동안구 호계3동 651-1번지 일원",
		"short_addr": "경기도 안양시",
		"addr_lv1": "경기도",
		"addr_lv2": "안양시",
		"apply_nums": "178세대"
	},
	{
		"link": "https://www.applyhome.co.kr/ai/aia/selectAPTLttotPblancDetail.do?houseManageNo=2022000601&pblancNo=2022000601&houseSecd=01",
		"in_date": "20220915",
		"hsecd": "01",
		"rse": "03",
		"type": "APT 2순위",
		"name": "광혜원 포레가",
		"addr": "충청북도 진천군 광혜원면 화랑길 64-14",
		"short_addr": "충청북도 진천군",
		"addr_lv1": "충청북도",
		"addr_lv2": "진천군",
		"apply_nums": "51세대"
	},
	{
		"link": "https://www.applyhome.co.kr/ai/aia/selectAPTLttotPblancDetail.do?houseManageNo=2022000575&pblancNo=2022000575&houseSecd=01",
		"in_date": "20220915",
		"hsecd": "01",
		"rse": "03",
		"type": "APT 2순위",
		"name": "양양 스위트엠 디오션",
		"addr": "강원도 양양군 양양읍 청곡리 87-7 번지 외 16필지 ",
		"short_addr": "강원도 양양군",
		"addr_lv1": "강원도",
		"addr_lv2": "양양군",
		"apply_nums": "209세대"
	},
	{
		"link": "https://www.applyhome.co.kr/ai/aia/selectAPTLttotPblancDetail.do?houseManageNo=2022850019&pblancNo=2022850019&houseSecd=03",
		"in_date": "20220915",
		"hsecd": "03",
		"rse": "04",
		"type": "",
		"name": "서울은평뉴타운 디에트르 더 퍼스트"
	},
	{
		"link": "https://www.applyhome.co.kr/ai/aia/selectAPTLttotPblancDetail.do?houseManageNo=2022000602&pblancNo=2022000602&houseSecd=01",
		"in_date": "20220916",
		"hsecd": "01",
		"rse": "03",
		"type": "APT 2순위",
		"name": "e편한세상 주촌 더프리미어",
		"addr": "경상남도 김해시 주촌면 선지리213-2번지 일원",
		"short_addr": "경상남도 김해시",
		"addr_lv1": "경상남도",
		"addr_lv2": "김해시",
		"apply_nums": "992세대"
	},
	{
		"link": "https://www.applyhome.co.kr/ai/aia/selectAPTLttotPblancDetail.do?houseManageNo=2022000490&pblancNo=2022000490&houseSecd=01",
		"in_date": "20220916",
		"hsecd": "01",
		"rse": "03",
		"type": "APT 2순위",
		"name": "구서다움파크",
		"addr": "부산광역시 금정구 중앙대로1893번길 50(구서동)",
		"short_addr": "부산광역시 금정구",
		"addr_lv1": "부산광역시",
		"addr_lv2": "금정구",
		"apply_nums": "84세대"
	},
	{
		"link": "https://www.applyhome.co.kr/ai/aia/selectAPTLttotPblancDetail.do?houseManageNo=2022000557&pblancNo=2022000557&houseSecd=01",
		"in_date": "20220916",
		"hsecd": "01",
		"rse": "03",
		"type": "APT 2순위",
		"name": "평촌 두산위브 더 프라임",
		"addr": "경기도 안양시 동안구 호계3동 651-1번지 일원",
		"short_addr": "경기도 안양시",
		"addr_lv1": "경기도",
		"addr_lv2": "안양시",
		"apply_nums": "178세대"
	},
	{
		"link": "https://www.applyhome.co.kr/ai/aia/selectAPTLttotPblancDetail.do?houseManageNo=2022850019&pblancNo=2022850019&houseSecd=03",
		"in_date": "20220916",
		"hsecd": "03",
		"rse": "04",
		"type": "",
		"name": "서울은평뉴타운 디에트르 더 퍼스트"
	},
	{
		"link": "https://www.applyhome.co.kr/ai/aia/selectAPTLttotPblancDetail.do?houseManageNo=2022000582&pblancNo=2022000582&houseSecd=01",
		"in_date": "20220919",
		"hsecd": "01",
		"rse": "01",
		"type": "APT 특별공급",
		"name": "인덕원 자이 SK VIEW",
		"addr": "경기도 의왕시 내손동 683번지 일원",
		"short_addr": "경기도 의왕시",
		"addr_lv1": "경기도",
		"addr_lv2": "의왕시",
		"apply_nums": "899세대"
	},
	{
		"link": "https://www.applyhome.co.kr/ai/aia/selectPRMOLttotPblancDetailView.do?houseManageNo=2022950088&pblancNo=2022950088&houseSecd=02",
		"in_date": "20220919",
		"hsecd": "02",
		"rse": "05",
		"type": "오피스텔/도시형생활주택/민간임대",
		"name": "백운호수 푸르지오 숲속의 아침 1단지",
		"addr": "경기도 의왕시 학의동 661번지 일원",
		"short_addr": "경기도 의왕시",
		"addr_lv1": "경기도",
		"addr_lv2": "의왕시",
		"apply_nums": "512세대"
	},
	{
		"link": "https://www.applyhome.co.kr/ai/aia/selectPRMOLttotPblancDetailView.do?houseManageNo=2022950089&pblancNo=2022950089&houseSecd=02",
		"in_date": "20220919",
		"hsecd": "02",
		"rse": "05",
		"type": "오피스텔/도시형생활주택/민간임대",
		"name": "백운호수 푸르지오 숲속의 아침 2단지",
		"addr": "경기도 의왕시 학의동 656-1번지 일원",
		"short_addr": "경기도 의왕시",
		"addr_lv1": "경기도",
		"addr_lv2": "의왕시",
		"apply_nums": "330세대"
	},
	{
		"link": "https://www.applyhome.co.kr/ai/aia/selectAPTRemndrLttotPblancDetailView.do?houseManageNo=2022910295&pblancNo=2022910295&houseSecd=04",
		"in_date": "20220919",
		"hsecd": "04",
		"rse": "06",
		"type": "무순위/취소후재공급",
		"name": "e편한세상 평택 하이센트(4BL)",
		"addr": "경기도 평택시 현덕면 화양리 평택화양지구 공동 4BL",
		"short_addr": "경기도 평택시",
		"addr_lv1": "경기도",
		"addr_lv2": "평택시",
		"apply_nums": "87세대"
	},
	{
		"link": "https://www.applyhome.co.kr/ai/aia/selectAPTRemndrLttotPblancDetailView.do?houseManageNo=2022910289&pblancNo=2022910289&houseSecd=04",
		"in_date": "20220919",
		"hsecd": "04",
		"rse": "06",
		"type": "무순위/취소후재공급",
		"name": "가능역 하우스토리 리버블리스",
		"addr": "경기도 의정부시 가능동 15-14(태평로214번길 29-9)",
		"short_addr": "경기도 의정부시",
		"addr_lv1": "경기도",
		"addr_lv2": "의정부시",
		"apply_nums": "48세대"
	},
	{
		"link": "https://www.applyhome.co.kr/ai/aia/selectAPTRemndrLttotPblancDetailView.do?houseManageNo=2022910293&pblancNo=2022910293&houseSecd=04",
		"in_date": "20220919",
		"hsecd": "04",
		"rse": "06",
		"type": "무순위/취소후재공급",
		"name": "이안 모란 센트럴파크",
		"addr": "경기도 성남시 중원구 하대원동 147-5번지",
		"short_addr": "경기도 성남시",
		"addr_lv1": "경기도",
		"addr_lv2": "성남시",
		"apply_nums": "1세대"
	},
	{
		"link": "https://www.applyhome.co.kr/ai/aia/selectAPTLttotPblancDetail.do?houseManageNo=2022000582&pblancNo=2022000582&houseSecd=01",
		"in_date": "20220920",
		"hsecd": "01",
		"rse": "02",
		"type": "APT 1순위",
		"name": "인덕원 자이 SK VIEW",
		"addr": "경기도 의왕시 내손동 683번지 일원",
		"short_addr": "경기도 의왕시",
		"addr_lv1": "경기도",
		"addr_lv2": "의왕시",
		"apply_nums": "899세대"
	},
	{
		"link": "https://www.applyhome.co.kr/ai/aia/selectAPTLttotPblancDetail.do?houseManageNo=2022000582&pblancNo=2022000582&houseSecd=01",
		"in_date": "20220921",
		"hsecd": "01",
		"rse": "02",
		"type": "APT 1순위",
		"name": "인덕원 자이 SK VIEW",
		"addr": "경기도 의왕시 내손동 683번지 일원",
		"short_addr": "경기도 의왕시",
		"addr_lv1": "경기도",
		"addr_lv2": "의왕시",
		"apply_nums": "899세대"
	},
	{
		"link": "https://www.applyhome.co.kr/ai/aia/selectAPTLttotPblancDetail.do?houseManageNo=2022000582&pblancNo=2022000582&houseSecd=01",
		"in_date": "20220922",
		"hsecd": "01",
		"rse": "03",
		"type": "APT 2순위",
		"name": "인덕원 자이 SK VIEW",
		"addr": "경기도 의왕시 내손동 683번지 일원",
		"short_addr": "경기도 의왕시",
		"addr_lv1": "경기도",
		"addr_lv2": "의왕시",
		"apply_nums": "899세대"
	}
]